odoo9_addon_product_pricelist_item_list_view-9.0.1.0.0-py2.7-nspkg.pth
odoo9_addon_product_pricelist_item_list_view-9.0.1.0.0.dist-info/DESCRIPTION.rst
odoo9_addon_product_pricelist_item_list_view-9.0.1.0.0.dist-info/METADATA
odoo9_addon_product_pricelist_item_list_view-9.0.1.0.0.dist-info/RECORD
odoo9_addon_product_pricelist_item_list_view-9.0.1.0.0.dist-info/WHEEL
odoo9_addon_product_pricelist_item_list_view-9.0.1.0.0.dist-info/metadata.json
odoo9_addon_product_pricelist_item_list_view-9.0.1.0.0.dist-info/namespace_packages.txt
odoo9_addon_product_pricelist_item_list_view-9.0.1.0.0.dist-info/top_level.txt
odoo_addons/product_pricelist_item_list_view/README.rst
odoo_addons/product_pricelist_item_list_view/__init__.py
odoo_addons/product_pricelist_item_list_view/__openerp__.py
odoo_addons/product_pricelist_item_list_view/static/description/icon.png
odoo_addons/product_pricelist_item_list_view/views/pricelist_view.xml
