Metadata-Version: 2.0
Name: odoo9-addon-product-pricelist-item-list-view
Version: 9.0.1.0.0
Summary: View and search the list of pricelist items
Home-page: https://www.agilebg.com
Author: Agile Business Group, Odoo Community Association (OCA)
Author-email: support@odoo-community.org
License: LGPL-3
Platform: UNKNOWN
Classifier: Programming Language :: Python :: 2.7
Classifier: Framework :: Odoo
Classifier: License :: OSI Approved :: GNU Lesser General Public License v3 (LGPLv3)
Requires-Dist: odoo (<9.1a,>=9.0a)
